{
  "trade_id": "SIM-1765989664-000257",
  "run_tag": "replay_20251217_163933",
  "policy_sha256": "N/A",
  "router_sha256": "N/A",
  "manifest_sha256": "N/A",
  "entry_snapshot": {
    "trade_id": "SIM-1765989664-000257",
    "entry_time": "2025-01-30T07:25:00+00:00",
    "instrument": "XAU_USD",
    "side": "long",
    "entry_price": 2766.89,
    "session": "EU",
    "regime": null,
    "entry_model_version": "ENTRY_V9",
    "entry_score": {
      "p_long": 0.9480942487716675,
      "p_short": 0.05190575122833252,
      "p_hat": 0.9480942487716675,
      "margin": 0.896188497543335
    },
    "entry_filters_passed": [
      "spread_ok",
      "atr_ok",
      "session_ok"
    ],
    "entry_filters_blocked": [],
    "test_mode": false
  },
  "feature_context": {
    "atr": {
      "atr_bps": 6.024326568379963,
      "atr_price": 1.6668648938784836,
      "atr_percentile": 58.11688311688312
    },
    "range": {
      "range_pos": 0.9519576719576627,
      "distance_to_range": 0.09608465608467465,
      "range_edge_dist_atr": 0.6809190139935607
    },
    "spread": {
      "spread_price": 0.5,
      "spread_pct": 53.515625
    },
    "candle": {
      "close": 2766.64,
      "high": 2767.555,
      "low": 2766.12
    }
  },
  "router_explainability": null,
  "exit_configuration": {
    "exit_profile": "SNIPER_EXIT_RULES_A",
    "tp_levels": [
      5.0,
      9.0
    ],
    "sl": 4.0,
    "trailing_enabled": true,
    "be_rules": {
      "adaptive_threshold_bps": 4.0,
      "trailing_stop_bps": 2.0
    }
  },
  "exit_events": [
    {
      "timestamp": "2025-01-30T07:50:00+00:00",
      "event_type": "EXIT_TRIGGERED",
      "price": 2768.61,
      "pnl_bps": 6.216365666868776,
      "bars_held": 6
    }
  ],
  "execution_events": [],
  "exit_summary": {
    "exit_time": "2025-01-30T07:50:00+00:00",
    "exit_price": 2768.61,
    "exit_reason": "RULE_A_PROFIT",
    "realized_pnl_bps": 6.216365666868776,
    "max_mfe_bps": 8.294511165966384,
    "max_mae_bps": -5.710382414913232,
    "intratrade_drawdown_bps": 2.349207955502716
  }
}