{
  "trade_id": "SIM-1765978597-001095",
  "run_tag": "replay_20251217_132717",
  "policy_sha256": "N/A",
  "router_sha256": "N/A",
  "manifest_sha256": "N/A",
  "entry_snapshot": {
    "trade_id": "SIM-1765978597-001095",
    "entry_time": "2025-03-28T17:05:00+00:00",
    "instrument": "XAU_USD",
    "side": "long",
    "entry_price": 3085.64,
    "session": "US",
    "regime": null,
    "entry_model_version": "ENTRY_V9",
    "entry_score": {
      "p_long": 0.7126181125640869,
      "p_short": 0.2873818874359131,
      "p_hat": 0.7126181125640869,
      "margin": 0.42523622512817383
    },
    "entry_filters_passed": [
      "spread_ok",
      "atr_ok",
      "session_ok"
    ],
    "entry_filters_blocked": [],
    "test_mode": false
  },
  "feature_context": {
    "atr": {
      "atr_bps": 7.536781600945975,
      "atr_price": 2.3255794779142938,
      "atr_percentile": 61.16666666666667
    },
    "range": {
      "range_pos": 0.8989538147486608,
      "distance_to_range": 0.20209237050267848,
      "range_edge_dist_atr": 0.8514007019772079
    },
    "spread": {
      "spread_price": 0.5899999999996908,
      "spread_pct": 85.0
    },
    "candle": {
      "close": 3085.345,
      "high": 3085.97,
      "low": 3084.82
    }
  },
  "router_explainability": null,
  "exit_configuration": null,
  "exit_events": [],
  "execution_events": [],
  "exit_summary": null
}