{
  "trade_id": "SIM-1765980493-001064",
  "run_tag": "replay_20251217_140118",
  "policy_sha256": "N/A",
  "router_sha256": "N/A",
  "manifest_sha256": "N/A",
  "entry_snapshot": {
    "trade_id": "SIM-1765980493-001064",
    "entry_time": "2025-03-27T19:10:00+00:00",
    "instrument": "XAU_USD",
    "side": "long",
    "entry_price": 3057.41,
    "session": "US",
    "regime": null,
    "entry_model_version": "ENTRY_V9",
    "entry_score": {
      "p_long": 0.8671938180923462,
      "p_short": 0.1328061819076538,
      "p_hat": 0.8671938180923462,
      "margin": 0.7343876361846924
    },
    "entry_filters_passed": [
      "spread_ok",
      "atr_ok",
      "session_ok"
    ],
    "entry_filters_blocked": [],
    "test_mode": false
  },
  "feature_context": {
    "atr": {
      "atr_bps": 3.809632845320436,
      "atr_price": 1.1647609557611154,
      "atr_percentile": 7.833333333333334
    },
    "range": {
      "range_pos": 0.872336377473364,
      "distance_to_range": 0.255327245053272,
      "range_edge_dist_atr": 2.8804193542079086
    },
    "spread": {
      "spread_price": 0.6199999999998909,
      "spread_pct": 95.0
    },
    "candle": {
      "close": 3057.1,
      "high": 3057.31,
      "low": 3056.39
    }
  },
  "router_explainability": null,
  "exit_configuration": null,
  "exit_events": [],
  "execution_events": [],
  "exit_summary": null
}