{
  "trade_id": "SIM-1765973391-003443",
  "run_tag": "replay_20251217_112631",
  "policy_sha256": "N/A",
  "router_sha256": "N/A",
  "manifest_sha256": "N/A",
  "entry_snapshot": {
    "trade_id": "SIM-1765973391-003443",
    "entry_time": "2025-02-12T18:40:00+00:00",
    "instrument": "XAU_USD",
    "side": "long",
    "entry_price": 2901.94,
    "session": "US",
    "regime": null,
    "entry_model_version": "ENTRY_V9",
    "entry_score": {
      "p_long": 0.9356522560119629,
      "p_short": 0.06434774398803711,
      "p_hat": 0.9356522560119629,
      "margin": 0.8713045120239258
    },
    "entry_filters_passed": [
      "spread_ok",
      "atr_ok",
      "session_ok"
    ],
    "entry_filters_blocked": [],
    "test_mode": false
  },
  "feature_context": {
    "atr": {
      "atr_bps": 5.899291838816228,
      "atr_price": 1.7119390958734366,
      "atr_percentile": 22.5
    },
    "range": {
      "range_pos": 0.8606876599532709,
      "distance_to_range": 0.2786246800934582,
      "range_edge_dist_atr": 3.6566721416020305
    },
    "spread": {
      "spread_price": 0.5199999999999818,
      "spread_pct": 53.166666666666664
    },
    "candle": {
      "close": 2901.68,
      "high": 2903.205,
      "low": 2901.32
    }
  },
  "router_explainability": null,
  "exit_configuration": null,
  "exit_events": [],
  "execution_events": [],
  "exit_summary": null
}