{
  "trade_id": "SIM-1765980166-000340",
  "run_tag": "replay_20251217_140118",
  "policy_sha256": "N/A",
  "router_sha256": "N/A",
  "manifest_sha256": "N/A",
  "entry_snapshot": {
    "trade_id": "SIM-1765980166-000340",
    "entry_time": "2025-01-06T15:10:00+00:00",
    "instrument": "XAU_USD",
    "side": "long",
    "entry_price": 2631.93,
    "session": "OVERLAP",
    "regime": null,
    "entry_model_version": "ENTRY_V9",
    "entry_score": {
      "p_long": 0.9507138133049011,
      "p_short": 0.04928618669509888,
      "p_hat": 0.9507138133049011,
      "margin": 0.9014276266098022
    },
    "entry_filters_passed": [
      "spread_ok",
      "atr_ok",
      "session_ok"
    ],
    "entry_filters_blocked": [],
    "test_mode": false
  },
  "feature_context": {
    "atr": {
      "atr_bps": 18.952985305532824,
      "atr_price": 4.988293061519101,
      "atr_percentile": 96.93593314763231
    },
    "range": {
      "range_pos": 0.5076680521714119,
      "distance_to_range": 0.9846638956571763,
      "range_edge_dist_atr": 3.443061541931505
    },
    "spread": {
      "spread_price": 0.4600000000000364,
      "spread_pct": 23.303834808259587
    },
    "candle": {
      "close": 2631.7,
      "high": 2632.995,
      "low": 2630.2
    }
  },
  "router_explainability": null,
  "exit_configuration": null,
  "exit_events": [],
  "execution_events": [],
  "exit_summary": null
}