{
  "trade_id": "SIM-1765978236-000557",
  "run_tag": "replay_20251217_132717",
  "policy_sha256": "N/A",
  "router_sha256": "N/A",
  "manifest_sha256": "N/A",
  "entry_snapshot": {
    "trade_id": "SIM-1765978236-000557",
    "entry_time": "2025-02-13T14:40:00+00:00",
    "instrument": "XAU_USD",
    "side": "long",
    "entry_price": 2914.69,
    "session": "OVERLAP",
    "regime": null,
    "entry_model_version": "ENTRY_V9",
    "entry_score": {
      "p_long": 0.8346299529075623,
      "p_short": 0.16537004709243774,
      "p_hat": 0.8346299529075623,
      "margin": 0.6692599058151245
    },
    "entry_filters_passed": [
      "spread_ok",
      "atr_ok",
      "session_ok"
    ],
    "entry_filters_blocked": [],
    "test_mode": false
  },
  "feature_context": {
    "atr": {
      "atr_bps": 11.73712372090102,
      "atr_price": 3.4210077138072994,
      "atr_percentile": 85.66666666666667
    },
    "range": {
      "range_pos": 0.6281645569620404,
      "distance_to_range": 0.7436708860759191,
      "range_edge_dist_atr": 2.0607962886332283
    },
    "spread": {
      "spread_price": 0.5,
      "spread_pct": 44.7841726618705
    },
    "candle": {
      "close": 2914.44,
      "high": 2916.455,
      "low": 2913.32
    }
  },
  "router_explainability": null,
  "exit_configuration": {
    "exit_profile": "SNIPER_EXIT_RULES_A",
    "tp_levels": [
      5.0,
      9.0
    ],
    "sl": 4.0,
    "trailing_enabled": true,
    "be_rules": {
      "adaptive_threshold_bps": 4.0,
      "trailing_stop_bps": 2.0
    }
  },
  "exit_events": [
    {
      "timestamp": "2025-02-13T14:55:00+00:00",
      "event_type": "EXIT_TRIGGERED",
      "price": 2914.93,
      "pnl_bps": 0.8234151830890479,
      "bars_held": 4
    }
  ],
  "execution_events": [],
  "exit_summary": {
    "exit_time": "2025-02-13T14:55:00+00:00",
    "exit_price": 2914.93,
    "exit_reason": "RULE_A_TRAILING",
    "realized_pnl_bps": 0.8234151830890479,
    "max_mfe_bps": 9.64081943534285,
    "max_mae_bps": -4.700328336803882,
    "intratrade_drawdown_bps": 5.5408980028759025
  }
}