{
  "trade_id": "SIM-1765978114-000304",
  "run_tag": "replay_20251217_132717",
  "policy_sha256": "N/A",
  "router_sha256": "N/A",
  "manifest_sha256": "N/A",
  "entry_snapshot": {
    "trade_id": "SIM-1765978114-000304",
    "entry_time": "2025-03-07T15:40:00+00:00",
    "instrument": "XAU_USD",
    "side": "long",
    "entry_price": 2914.83,
    "session": "OVERLAP",
    "regime": null,
    "entry_model_version": "ENTRY_V9",
    "entry_score": {
      "p_long": 0.7635040879249573,
      "p_short": 0.23649591207504272,
      "p_hat": 0.7635040879249573,
      "margin": 0.5270081758499146
    },
    "entry_filters_passed": [
      "spread_ok",
      "atr_ok",
      "session_ok"
    ],
    "entry_filters_blocked": [],
    "test_mode": false
  },
  "feature_context": {
    "atr": {
      "atr_bps": 14.772248808049484,
      "atr_price": 4.305859399316687,
      "atr_percentile": 95.08196721311475
    },
    "range": {
      "range_pos": 0.6098839385997732,
      "distance_to_range": 0.7802321228004536,
      "range_edge_dist_atr": 2.419958255407425
    },
    "spread": {
      "spread_price": 0.6799999999998363,
      "spread_pct": 89.76897689768977
    },
    "candle": {
      "close": 2914.49,
      "high": 2920.015,
      "low": 2912.535
    }
  },
  "router_explainability": null,
  "exit_configuration": {
    "exit_profile": "SNIPER_EXIT_RULES_A",
    "tp_levels": [
      5.0,
      9.0
    ],
    "sl": 4.0,
    "trailing_enabled": true,
    "be_rules": {
      "adaptive_threshold_bps": 4.0,
      "trailing_stop_bps": 2.0
    }
  },
  "exit_events": [
    {
      "timestamp": "2025-03-07T16:20:00+00:00",
      "event_type": "EXIT_TRIGGERED",
      "price": 2916.63,
      "pnl_bps": 6.175317256924698,
      "bars_held": 9
    }
  ],
  "execution_events": [],
  "exit_summary": {
    "exit_time": "2025-03-07T16:20:00+00:00",
    "exit_price": 2916.63,
    "exit_reason": "RULE_A_PROFIT",
    "realized_pnl_bps": 6.175317256924698,
    "max_mfe_bps": 17.78834443175055,
    "max_mae_bps": -21.167615264012216,
    "intratrade_drawdown_bps": 10.446578359628583
  }
}