{
  "trade_id": "SIM-1765989625-000161",
  "run_tag": "replay_20251217_163933",
  "policy_sha256": "N/A",
  "router_sha256": "N/A",
  "manifest_sha256": "N/A",
  "entry_snapshot": {
    "trade_id": "SIM-1765989625-000161",
    "entry_time": "2025-03-06T18:40:00+00:00",
    "instrument": "XAU_USD",
    "side": "long",
    "entry_price": 2914.3,
    "session": "US",
    "regime": null,
    "entry_model_version": "ENTRY_V9",
    "entry_score": {
      "p_long": 0.968096137046814,
      "p_short": 0.031903862953186035,
      "p_hat": 0.968096137046814,
      "margin": 0.9361922740936279
    },
    "entry_filters_passed": [
      "spread_ok",
      "atr_ok",
      "session_ok"
    ],
    "entry_filters_blocked": [],
    "test_mode": false
  },
  "feature_context": {
    "atr": {
      "atr_bps": 7.2824517669320254,
      "atr_price": 2.1223249184370006,
      "atr_percentile": 21.73913043478261
    },
    "range": {
      "range_pos": 0.8166770122077449,
      "distance_to_range": 0.3666459755845102,
      "range_edge_dist_atr": 2.0873335470528884
    },
    "spread": {
      "spread_price": 0.5,
      "spread_pct": 33.125
    },
    "candle": {
      "close": 2914.05,
      "high": 2918.38,
      "low": 2914.045
    }
  },
  "router_explainability": null,
  "exit_configuration": null,
  "exit_events": [],
  "execution_events": [],
  "exit_summary": null
}