{
  "trade_id": "SIM-1765978072-000122",
  "run_tag": "replay_20251217_132717",
  "policy_sha256": "N/A",
  "router_sha256": "N/A",
  "manifest_sha256": "N/A",
  "entry_snapshot": {
    "trade_id": "SIM-1765978072-000122",
    "entry_time": "2025-01-16T08:40:00+00:00",
    "instrument": "XAU_USD",
    "side": "long",
    "entry_price": 2699.83,
    "session": "EU",
    "regime": null,
    "entry_model_version": "ENTRY_V9",
    "entry_score": {
      "p_long": 0.9204028844833374,
      "p_short": 0.0795971155166626,
      "p_hat": 0.9204028844833374,
      "margin": 0.8408057689666748
    },
    "entry_filters_passed": [
      "spread_ok",
      "atr_ok",
      "session_ok"
    ],
    "entry_filters_blocked": [],
    "test_mode": false
  },
  "feature_context": {
    "atr": {
      "atr_bps": 7.400772887293731,
      "atr_price": 1.9980828664302233,
      "atr_percentile": 61.31386861313869
    },
    "range": {
      "range_pos": 0.8757811020640115,
      "distance_to_range": 0.248437795871977,
      "range_edge_dist_atr": 1.6415735578874147
    },
    "spread": {
      "spread_price": 0.6100000000001273,
      "spread_pct": 82.64462809917356
    },
    "candle": {
      "close": 2699.525,
      "high": 2700.385,
      "low": 2699.38
    }
  },
  "router_explainability": null,
  "exit_configuration": {
    "exit_profile": "SNIPER_EXIT_RULES_A",
    "tp_levels": [
      5.0,
      9.0
    ],
    "sl": 4.0,
    "trailing_enabled": true,
    "be_rules": {
      "adaptive_threshold_bps": 4.0,
      "trailing_stop_bps": 2.0
    }
  },
  "exit_events": [
    {
      "timestamp": "2025-01-16T09:10:00+00:00",
      "event_type": "EXIT_TRIGGERED",
      "price": 2701.56,
      "pnl_bps": 6.407810862165463,
      "bars_held": 7
    }
  ],
  "execution_events": [],
  "exit_summary": {
    "exit_time": "2025-01-16T09:10:00+00:00",
    "exit_price": 2701.56,
    "exit_reason": "RULE_A_PROFIT",
    "realized_pnl_bps": 6.407810862165463,
    "max_mfe_bps": 8.574613957175284,
    "max_mae_bps": -8.333858057729561,
    "intratrade_drawdown_bps": 5.62998411011057
  }
}