{
  "trade_id": "SIM-1765978300-000717",
  "run_tag": "replay_20251217_132717",
  "policy_sha256": "N/A",
  "router_sha256": "N/A",
  "manifest_sha256": "N/A",
  "entry_snapshot": {
    "trade_id": "SIM-1765978300-000717",
    "entry_time": "2025-01-08T19:00:00+00:00",
    "instrument": "XAU_USD",
    "side": "long",
    "entry_price": 2654.26,
    "session": "US",
    "regime": null,
    "entry_model_version": "ENTRY_V9",
    "entry_score": {
      "p_long": 0.8991603851318359,
      "p_short": 0.10083961486816406,
      "p_hat": 0.8991603851318359,
      "margin": 0.7983207702636719
    },
    "entry_filters_passed": [
      "spread_ok",
      "atr_ok",
      "session_ok"
    ],
    "entry_filters_blocked": [],
    "test_mode": false
  },
  "feature_context": {
    "atr": {
      "atr_bps": 8.638165430758974,
      "atr_price": 2.2927936976246315,
      "atr_percentile": 66.83333333333333
    },
    "range": {
      "range_pos": 0.3079777365491555,
      "distance_to_range": 0.615955473098311,
      "range_edge_dist_atr": 3.2580340777012915
    },
    "spread": {
      "spread_price": 0.680000000000291,
      "spread_pct": 98.33333333333333
    },
    "candle": {
      "close": 2653.92,
      "high": 2654.315,
      "low": 2652.635
    }
  },
  "router_explainability": null,
  "exit_configuration": null,
  "exit_events": [],
  "execution_events": [],
  "exit_summary": null
}