{
  "trade_id": "SIM-1765975252-004902",
  "run_tag": "replay_20251217_112631",
  "policy_sha256": "N/A",
  "router_sha256": "N/A",
  "manifest_sha256": "N/A",
  "entry_snapshot": {
    "trade_id": "SIM-1765975252-004902",
    "entry_time": "2025-02-27T09:05:00+00:00",
    "instrument": "XAU_USD",
    "side": "long",
    "entry_price": 2880.09,
    "session": "EU",
    "regime": null,
    "entry_model_version": "ENTRY_V9",
    "entry_score": {
      "p_long": 0.89492267370224,
      "p_short": 0.10507732629776001,
      "p_hat": 0.89492267370224,
      "margin": 0.78984534740448
    },
    "entry_filters_passed": [
      "spread_ok",
      "atr_ok",
      "session_ok"
    ],
    "entry_filters_blocked": [],
    "test_mode": false
  },
  "feature_context": {
    "atr": {
      "atr_bps": 12.180799676568133,
      "atr_price": 3.508179934048712,
      "atr_percentile": 87.5
    },
    "range": {
      "range_pos": 0.012572161642084351,
      "distance_to_range": 0.025144323284168702,
      "range_edge_dist_atr": 0.13967356555589738
    },
    "spread": {
      "spread_price": 0.5300000000002001,
      "spread_pct": 72.16666666666667
    },
    "candle": {
      "close": 2879.825,
      "high": 2881.82,
      "low": 2877.17
    }
  },
  "router_explainability": null,
  "exit_configuration": null,
  "exit_events": [],
  "execution_events": [],
  "exit_summary": null
}