{
  "trade_id": "SIM-1765978052-000065",
  "run_tag": "replay_20251217_132717",
  "policy_sha256": "N/A",
  "router_sha256": "N/A",
  "manifest_sha256": "N/A",
  "entry_snapshot": {
    "trade_id": "SIM-1765978052-000065",
    "entry_time": "2025-03-06T10:40:00+00:00",
    "instrument": "XAU_USD",
    "side": "long",
    "entry_price": 2902.64,
    "session": "EU",
    "regime": null,
    "entry_model_version": "ENTRY_V9",
    "entry_score": {
      "p_long": 0.9723727107048035,
      "p_short": 0.027627289295196533,
      "p_hat": 0.9723727107048035,
      "margin": 0.9447454214096069
    },
    "entry_filters_passed": [
      "spread_ok",
      "atr_ok",
      "session_ok"
    ],
    "entry_filters_blocked": [],
    "test_mode": false
  },
  "feature_context": {
    "atr": {
      "atr_bps": 9.998021314673744,
      "atr_price": 2.9020656588824596,
      "atr_percentile": 64.61538461538461
    },
    "range": {
      "range_pos": 0.3759386733416727,
      "distance_to_range": 0.7518773466833454,
      "range_edge_dist_atr": 4.14015443214564
    },
    "spread": {
      "spread_price": 0.5599999999999454,
      "spread_pct": 60.9375
    },
    "candle": {
      "close": 2902.36,
      "high": 2904.2,
      "low": 2902.17
    }
  },
  "router_explainability": null,
  "exit_configuration": null,
  "exit_events": [],
  "execution_events": [],
  "exit_summary": null
}