{
  "trade_id": "SIM-1765973448-003507",
  "run_tag": "replay_20251217_112631",
  "policy_sha256": "N/A",
  "router_sha256": "N/A",
  "manifest_sha256": "N/A",
  "entry_snapshot": {
    "trade_id": "SIM-1765973448-003507",
    "entry_time": "2025-02-13T09:00:00+00:00",
    "instrument": "XAU_USD",
    "side": "long",
    "entry_price": 2911.25,
    "session": "EU",
    "regime": null,
    "entry_model_version": "ENTRY_V9",
    "entry_score": {
      "p_long": 0.9202423095703125,
      "p_short": 0.0797576904296875,
      "p_hat": 0.9202423095703125,
      "margin": 0.840484619140625
    },
    "entry_filters_passed": [
      "spread_ok",
      "atr_ok",
      "session_ok"
    ],
    "entry_filters_blocked": [],
    "test_mode": false
  },
  "feature_context": {
    "atr": {
      "atr_bps": 9.653007031923662,
      "atr_price": 2.810231672168776,
      "atr_percentile": 72.33333333333334
    },
    "range": {
      "range_pos": 0.6805483255249034,
      "distance_to_range": 0.6389033489501932,
      "range_edge_dist_atr": 3.2755306586150725
    },
    "spread": {
      "spread_price": 0.4800000000000182,
      "spread_pct": 35.333333333333336
    },
    "candle": {
      "close": 2911.01,
      "high": 2912.58,
      "low": 2910.975
    }
  },
  "router_explainability": null,
  "exit_configuration": null,
  "exit_events": [],
  "execution_events": [],
  "exit_summary": null
}