{
  "trade_id": "SIM-1765978239-000459",
  "run_tag": "replay_20251217_132717",
  "policy_sha256": "N/A",
  "router_sha256": "N/A",
  "manifest_sha256": "N/A",
  "entry_snapshot": {
    "trade_id": "SIM-1765978239-000459",
    "entry_time": "2025-01-21T07:10:00+00:00",
    "instrument": "XAU_USD",
    "side": "long",
    "entry_price": 2726.1,
    "session": "EU",
    "regime": null,
    "entry_model_version": "ENTRY_V9",
    "entry_score": {
      "p_long": 0.9814691543579102,
      "p_short": 0.018530845642089844,
      "p_hat": 0.9814691543579102,
      "margin": 0.9629383087158203
    },
    "entry_filters_passed": [
      "spread_ok",
      "atr_ok",
      "session_ok"
    ],
    "entry_filters_blocked": [],
    "test_mode": false
  },
  "feature_context": {
    "atr": {
      "atr_bps": 11.093647311372509,
      "atr_price": 3.0242391935532593,
      "atr_percentile": 92.33333333333333
    },
    "range": {
      "range_pos": 0.9599403366716366,
      "distance_to_range": 0.08011932665672683,
      "range_edge_dist_atr": 0.310821975326503
    },
    "spread": {
      "spread_price": 0.5599999999999454,
      "spread_pct": 58.73362445414847
    },
    "candle": {
      "close": 2725.82,
      "high": 2726.075,
      "low": 2723.615
    }
  },
  "router_explainability": null,
  "exit_configuration": {
    "exit_profile": "SNIPER_EXIT_RULES_A",
    "tp_levels": [
      5.0,
      9.0
    ],
    "sl": 4.0,
    "trailing_enabled": true,
    "be_rules": {
      "adaptive_threshold_bps": 4.0,
      "trailing_stop_bps": 2.0
    }
  },
  "exit_events": [
    {
      "timestamp": "2025-01-21T07:25:00+00:00",
      "event_type": "EXIT_TRIGGERED",
      "price": 2727.86,
      "pnl_bps": 6.456109460402107,
      "bars_held": 4
    }
  ],
  "execution_events": [],
  "exit_summary": {
    "exit_time": "2025-01-21T07:25:00+00:00",
    "exit_price": 2727.86,
    "exit_reason": "RULE_A_PROFIT",
    "realized_pnl_bps": 6.456109460402107,
    "max_mfe_bps": 7.629947544110368,
    "max_mae_bps": -9.11558636880572,
    "intratrade_drawdown_bps": 2.806206668868814
  }
}