{
  "trade_id": "SIM-1765989607-000111",
  "run_tag": "replay_20251217_163933",
  "policy_sha256": "N/A",
  "router_sha256": "N/A",
  "manifest_sha256": "N/A",
  "entry_snapshot": {
    "trade_id": "SIM-1765989607-000111",
    "entry_time": "2025-03-19T19:55:00+00:00",
    "instrument": "XAU_USD",
    "side": "long",
    "entry_price": 3048.26,
    "session": "US",
    "regime": null,
    "entry_model_version": "ENTRY_V9",
    "entry_score": {
      "p_long": 0.9471220374107361,
      "p_short": 0.052877962589263916,
      "p_hat": 0.9471220374107361,
      "margin": 0.8942440748214722
    },
    "entry_filters_passed": [
      "spread_ok",
      "atr_ok",
      "session_ok"
    ],
    "entry_filters_blocked": [],
    "test_mode": false
  },
  "feature_context": {
    "atr": {
      "atr_bps": 9.496719560055046,
      "atr_price": 2.89484703661334,
      "atr_percentile": 82.03125
    },
    "range": {
      "range_pos": 0.8460207612456866,
      "distance_to_range": 0.3079584775086268,
      "range_edge_dist_atr": 1.3834927888573603
    },
    "spread": {
      "spread_price": 0.43000000000029104,
      "spread_pct": 8.181818181818182
    },
    "candle": {
      "close": 3048.045,
      "high": 3048.57,
      "low": 3047.21
    }
  },
  "router_explainability": null,
  "exit_configuration": {
    "exit_profile": "SNIPER_EXIT_RULES_A",
    "tp_levels": [
      5.0,
      9.0
    ],
    "sl": 4.0,
    "trailing_enabled": true,
    "be_rules": {
      "adaptive_threshold_bps": 4.0,
      "trailing_stop_bps": 2.0
    }
  },
  "exit_events": [],
  "execution_events": [],
  "exit_summary": null
}