{
  "trade_id": "SIM-1765993557-000041",
  "run_tag": "replay_20251217_174548",
  "policy_sha256": "N/A",
  "router_sha256": "N/A",
  "manifest_sha256": "N/A",
  "entry_snapshot": {
    "trade_id": "SIM-1765993557-000041",
    "entry_time": "2025-01-15T18:40:00+00:00",
    "instrument": "XAU_USD",
    "side": "long",
    "entry_price": 2691.83,
    "session": "US",
    "regime": null,
    "vol_regime": "LOW",
    "trend_regime": "TREND_NEUTRAL",
    "entry_model_version": "ENTRY_V9",
    "entry_score": {
      "p_long": 0.9445479512214661,
      "p_short": 0.055452048778533936,
      "p_hat": 0.9445479512214661,
      "margin": 0.8890959024429321
    },
    "entry_filters_passed": [
      "spread_ok",
      "atr_ok",
      "session_ok"
    ],
    "entry_filters_blocked": [],
    "test_mode": false
  },
  "feature_context": {
    "atr": {
      "atr_bps": 5.9066245380351825,
      "atr_price": 1.5899629130219244,
      "atr_percentile": 2.4390243902439024
    },
    "range": {
      "range_pos": 0.8154484188698833,
      "distance_to_range": 0.36910316226023343,
      "range_edge_dist_atr": 2.2390459367594415
    },
    "spread": {
      "spread_price": 0.599999999999909,
      "spread_pct": 92.5
    },
    "candle": {
      "close": 2691.53,
      "high": 2692.66,
      "low": 2691.49
    }
  },
  "router_explainability": null,
  "exit_configuration": {
    "exit_profile": "SNIPER_EXIT_RULES_A",
    "tp_levels": [
      5.0,
      9.0
    ],
    "sl": 4.0,
    "trailing_enabled": true,
    "be_rules": {
      "adaptive_threshold_bps": 4.0,
      "trailing_stop_bps": 2.0
    }
  },
  "exit_events": [
    {
      "timestamp": "2025-01-15T18:55:00+00:00",
      "event_type": "EXIT_TRIGGERED",
      "price": 2693.84,
      "pnl_bps": 7.467039151804602,
      "bars_held": 4
    }
  ],
  "execution_events": [],
  "exit_summary": {
    "exit_time": "2025-01-15T18:55:00+00:00",
    "exit_price": 2693.84,
    "exit_reason": "RULE_A_PROFIT",
    "realized_pnl_bps": 7.467039151804602,
    "max_mfe_bps": 9.101614886528022,
    "max_mae_bps": -2.489013050601534,
    "intratrade_drawdown_bps": 1.281655973816326
  }
}