{
  "trade_id": "SIM-1765974778-004517",
  "run_tag": "replay_20251217_112631",
  "policy_sha256": "N/A",
  "router_sha256": "N/A",
  "manifest_sha256": "N/A",
  "entry_snapshot": {
    "trade_id": "SIM-1765974778-004517",
    "entry_time": "2025-02-24T18:45:00+00:00",
    "instrument": "XAU_USD",
    "side": "long",
    "entry_price": 2947.49,
    "session": "US",
    "regime": null,
    "entry_model_version": "ENTRY_V9",
    "entry_score": {
      "p_long": 0.9307785034179688,
      "p_short": 0.06922149658203125,
      "p_hat": 0.9307785034179688,
      "margin": 0.8615570068359375
    },
    "entry_filters_passed": [
      "spread_ok",
      "atr_ok",
      "session_ok"
    ],
    "entry_filters_blocked": [],
    "test_mode": false
  },
  "feature_context": {
    "atr": {
      "atr_bps": 4.784080209685275,
      "atr_price": 1.410102857724525,
      "atr_percentile": 7.666666666666666
    },
    "range": {
      "range_pos": 0.6201960784313747,
      "distance_to_range": 0.7596078431372506,
      "range_edge_dist_atr": 6.8682932928939495
    },
    "spread": {
      "spread_price": 0.4299999999998363,
      "spread_pct": 12.333333333333334
    },
    "candle": {
      "close": 2947.275,
      "high": 2947.66,
      "low": 2946.445
    }
  },
  "router_explainability": null,
  "exit_configuration": null,
  "exit_events": [],
  "execution_events": [],
  "exit_summary": null
}