{
  "trade_id": "SIM-1765980096-000046",
  "run_tag": "replay_20251217_140118",
  "policy_sha256": "N/A",
  "router_sha256": "N/A",
  "manifest_sha256": "N/A",
  "entry_snapshot": {
    "trade_id": "SIM-1765980096-000046",
    "entry_time": "2025-01-28T16:45:00+00:00",
    "instrument": "XAU_USD",
    "side": "long",
    "entry_price": 2759.22,
    "session": "US",
    "regime": null,
    "entry_model_version": "ENTRY_V9",
    "entry_score": {
      "p_long": 0.7792935967445374,
      "p_short": 0.22070640325546265,
      "p_hat": 0.7792935967445374,
      "margin": 0.5585871934890747
    },
    "entry_filters_passed": [
      "spread_ok",
      "atr_ok",
      "session_ok"
    ],
    "entry_filters_blocked": [],
    "test_mode": false
  },
  "feature_context": {
    "atr": {
      "atr_bps": 6.182014475099332,
      "atr_price": 1.7057537979983577,
      "atr_percentile": 53.333333333333336
    },
    "range": {
      "range_pos": 0.9464795432921027,
      "distance_to_range": 0.10704091341579458,
      "range_edge_dist_atr": 0.6595324608511194
    },
    "spread": {
      "spread_price": 0.5899999999996908,
      "spread_pct": 93.33333333333333
    },
    "candle": {
      "close": 2758.925,
      "high": 2759.235,
      "low": 2757.335
    }
  },
  "router_explainability": null,
  "exit_configuration": {
    "exit_profile": "SNIPER_EXIT_RULES_A",
    "tp_levels": [
      5.0,
      9.0
    ],
    "sl": 4.0,
    "trailing_enabled": true,
    "be_rules": {
      "adaptive_threshold_bps": 4.0,
      "trailing_stop_bps": 2.0
    }
  },
  "exit_events": [
    {
      "timestamp": "2025-01-29T08:05:00+00:00",
      "event_type": "EXIT_TRIGGERED",
      "price": 2760.96,
      "pnl_bps": 6.306129993259822,
      "bars_held": 77
    }
  ],
  "execution_events": [],
  "exit_summary": {
    "exit_time": "2025-01-29T08:05:00+00:00",
    "exit_price": 2760.96,
    "exit_reason": "RULE_A_PROFIT",
    "realized_pnl_bps": 6.306129993259822,
    "max_mfe_bps": 21.27412819565075,
    "max_mae_bps": -6.831640826029688,
    "intratrade_drawdown_bps": 25.69566761620926
  }
}