{
  "trade_id": "SIM-1765980210-000452",
  "run_tag": "replay_20251217_140118",
  "policy_sha256": "N/A",
  "router_sha256": "N/A",
  "manifest_sha256": "N/A",
  "entry_snapshot": {
    "trade_id": "SIM-1765980210-000452",
    "entry_time": "2025-02-12T19:20:00+00:00",
    "instrument": "XAU_USD",
    "side": "long",
    "entry_price": 2894.75,
    "session": "US",
    "regime": null,
    "entry_model_version": "ENTRY_V9",
    "entry_score": {
      "p_long": 0.9647718071937561,
      "p_short": 0.035228192806243896,
      "p_hat": 0.9647718071937561,
      "margin": 0.9295436143875122
    },
    "entry_filters_passed": [
      "spread_ok",
      "atr_ok",
      "session_ok"
    ],
    "entry_filters_blocked": [],
    "test_mode": false
  },
  "feature_context": {
    "atr": {
      "atr_bps": 6.127405617470983,
      "atr_price": 1.773730741117413,
      "atr_percentile": 25.051334702258725
    },
    "range": {
      "range_pos": 0.7078001557805793,
      "distance_to_range": 0.5843996884388414,
      "range_edge_dist_atr": 7.402476427582256
    },
    "spread": {
      "spread_price": 0.5199999999999818,
      "spread_pct": 52.328159645232816
    },
    "candle": {
      "close": 2894.49,
      "high": 2896.325,
      "low": 2893.83
    }
  },
  "router_explainability": null,
  "exit_configuration": null,
  "exit_events": [],
  "execution_events": [],
  "exit_summary": null
}