{
  "trade_id": "SIM-1765980095-000068",
  "run_tag": "replay_20251217_140118",
  "policy_sha256": "N/A",
  "router_sha256": "N/A",
  "manifest_sha256": "N/A",
  "entry_snapshot": {
    "trade_id": "SIM-1765980095-000068",
    "entry_time": "2025-03-06T10:55:00+00:00",
    "instrument": "XAU_USD",
    "side": "long",
    "entry_price": 2899.65,
    "session": "EU",
    "regime": null,
    "entry_model_version": "ENTRY_V9",
    "entry_score": {
      "p_long": 0.9722650051116943,
      "p_short": 0.027734994888305664,
      "p_hat": 0.9722650051116943,
      "margin": 0.9445300102233887
    },
    "entry_filters_passed": [
      "spread_ok",
      "atr_ok",
      "session_ok"
    ],
    "entry_filters_blocked": [],
    "test_mode": false
  },
  "feature_context": {
    "atr": {
      "atr_bps": 9.957759587853989,
      "atr_price": 2.887401758892082,
      "atr_percentile": 64.70588235294117
    },
    "range": {
      "range_pos": 0.32571964956194754,
      "distance_to_range": 0.6514392991238951,
      "range_edge_dist_atr": 3.605317468530687
    },
    "spread": {
      "spread_price": 0.5199999999999818,
      "spread_pct": 44.776119402985074
    },
    "candle": {
      "close": 2899.39,
      "high": 2902.625,
      "low": 2898.995
    }
  },
  "router_explainability": null,
  "exit_configuration": {
    "exit_profile": "SNIPER_EXIT_RULES_A",
    "tp_levels": [
      5.0,
      9.0
    ],
    "sl": 4.0,
    "trailing_enabled": true,
    "be_rules": {
      "adaptive_threshold_bps": 4.0,
      "trailing_stop_bps": 2.0
    }
  },
  "exit_events": [
    {
      "timestamp": "2025-03-06T11:10:00+00:00",
      "event_type": "EXIT_TRIGGERED",
      "price": 2899.7,
      "pnl_bps": 0.17243460417542517,
      "bars_held": 4
    }
  ],
  "execution_events": [],
  "exit_summary": {
    "exit_time": "2025-03-06T11:10:00+00:00",
    "exit_price": 2899.7,
    "exit_reason": "RULE_A_TRAILING",
    "realized_pnl_bps": 0.17243460417542517,
    "max_mfe_bps": 16.89859120928419,
    "max_mae_bps": -3.3279878606043676,
    "intratrade_drawdown_bps": 8.759677892159273
  }
}