{
  "trade_id": "SIM-1765971929-002286",
  "run_tag": "replay_20251217_112631",
  "policy_sha256": "N/A",
  "router_sha256": "N/A",
  "manifest_sha256": "N/A",
  "entry_snapshot": {
    "trade_id": "SIM-1765971929-002286",
    "entry_time": "2025-01-28T16:20:00+00:00",
    "instrument": "XAU_USD",
    "side": "long",
    "entry_price": 2757.73,
    "session": "US",
    "regime": null,
    "entry_model_version": "ENTRY_V9",
    "entry_score": {
      "p_long": 0.8186907172203064,
      "p_short": 0.1813092827796936,
      "p_hat": 0.8186907172203064,
      "margin": 0.6373814344406128
    },
    "entry_filters_passed": [
      "spread_ok",
      "atr_ok",
      "session_ok"
    ],
    "entry_filters_blocked": [],
    "test_mode": false
  },
  "feature_context": {
    "atr": {
      "atr_bps": 5.828984842774069,
      "atr_price": 1.6074766370463334,
      "atr_percentile": 34.5
    },
    "range": {
      "range_pos": 0.9624283591594239,
      "distance_to_range": 0.07514328168115214,
      "range_edge_dist_atr": 0.5505523250564385
    },
    "spread": {
      "spread_price": 0.4099999999998545,
      "spread_pct": 14.000000000000002
    },
    "candle": {
      "close": 2757.525,
      "high": 2757.77,
      "low": 2756.572
    }
  },
  "router_explainability": null,
  "exit_configuration": null,
  "exit_events": [],
  "execution_events": [],
  "exit_summary": null
}