{
  "trade_id": "SIM-1765990378-001271",
  "run_tag": "replay_20251217_163933",
  "policy_sha256": "N/A",
  "router_sha256": "N/A",
  "manifest_sha256": "N/A",
  "entry_snapshot": {
    "trade_id": "SIM-1765990378-001271",
    "entry_time": "2025-01-14T18:45:00+00:00",
    "instrument": "XAU_USD",
    "side": "long",
    "entry_price": 2671.85,
    "session": "US",
    "regime": null,
    "entry_model_version": "ENTRY_V9",
    "entry_score": {
      "p_long": 0.9790889620780945,
      "p_short": 0.020911037921905518,
      "p_hat": 0.9790889620780945,
      "margin": 0.958177924156189
    },
    "entry_filters_passed": [
      "spread_ok",
      "atr_ok",
      "session_ok"
    ],
    "entry_filters_blocked": [],
    "test_mode": false
  },
  "feature_context": {
    "atr": {
      "atr_bps": 4.328566829970487,
      "atr_price": 1.1565281284656646,
      "atr_percentile": 7.333333333333333
    },
    "range": {
      "range_pos": 0.7901403628894179,
      "distance_to_range": 0.4197192742211642,
      "range_edge_dist_atr": 2.650173328742388
    },
    "spread": {
      "spread_price": 0.4600000000000364,
      "spread_pct": 21.333333333333336
    },
    "candle": {
      "close": 2671.62,
      "high": 2671.72,
      "low": 2670.825
    }
  },
  "router_explainability": null,
  "exit_configuration": null,
  "exit_events": [],
  "execution_events": [],
  "exit_summary": null
}