{
  "trade_id": "SIM-1765989943-000723",
  "run_tag": "replay_20251217_163933",
  "policy_sha256": "N/A",
  "router_sha256": "N/A",
  "manifest_sha256": "N/A",
  "entry_snapshot": {
    "trade_id": "SIM-1765989943-000723",
    "entry_time": "2025-02-17T08:45:00+00:00",
    "instrument": "XAU_USD",
    "side": "long",
    "entry_price": 2901.24,
    "session": "EU",
    "regime": null,
    "entry_model_version": "ENTRY_V9",
    "entry_score": {
      "p_long": 0.8778597116470337,
      "p_short": 0.12214028835296631,
      "p_hat": 0.8778597116470337,
      "margin": 0.7557194232940674
    },
    "entry_filters_passed": [
      "spread_ok",
      "atr_ok",
      "session_ok"
    ],
    "entry_filters_blocked": [],
    "test_mode": false
  },
  "feature_context": {
    "atr": {
      "atr_bps": 7.754822049055543,
      "atr_price": 2.2498599921601903,
      "atr_percentile": 64.16666666666667
    },
    "range": {
      "range_pos": 0.7201429057502571,
      "distance_to_range": 0.5597141884994858,
      "range_edge_dist_atr": 3.6557830392382424
    },
    "spread": {
      "spread_price": 0.5599999999999454,
      "spread_pct": 75.83333333333333
    },
    "candle": {
      "close": 2900.96,
      "high": 2901.795,
      "low": 2898.07
    }
  },
  "router_explainability": null,
  "exit_configuration": null,
  "exit_events": [],
  "execution_events": [],
  "exit_summary": null
}