{
  "trade_id": "SIM-1765980088-000033",
  "run_tag": "replay_20251217_140118",
  "policy_sha256": "N/A",
  "router_sha256": "N/A",
  "manifest_sha256": "N/A",
  "entry_snapshot": {
    "trade_id": "SIM-1765980088-000033",
    "entry_time": "2025-02-10T11:30:00+00:00",
    "instrument": "XAU_USD",
    "side": "long",
    "entry_price": 2902.59,
    "session": "EU",
    "regime": null,
    "entry_model_version": "ENTRY_V9",
    "entry_score": {
      "p_long": 0.7676523923873901,
      "p_short": 0.23234760761260986,
      "p_hat": 0.7676523923873901,
      "margin": 0.5353047847747803
    },
    "entry_filters_passed": [
      "spread_ok",
      "atr_ok",
      "session_ok"
    ],
    "entry_filters_blocked": [],
    "test_mode": false
  },
  "feature_context": {
    "atr": {
      "atr_bps": 6.993113696486416,
      "atr_price": 2.029814188428451,
      "atr_percentile": 48.484848484848484
    },
    "range": {
      "range_pos": 0.8703154774507729,
      "distance_to_range": 0.25936904509845427,
      "range_edge_dist_atr": 3.0175175811250865
    },
    "spread": {
      "spread_price": 0.49000000000023647,
      "spread_pct": 40.625
    },
    "candle": {
      "close": 2902.345,
      "high": 2902.42,
      "low": 2900.02
    }
  },
  "router_explainability": null,
  "exit_configuration": null,
  "exit_events": [],
  "execution_events": [],
  "exit_summary": null
}