{
  "trade_id": "SIM-1765974369-004145",
  "run_tag": "replay_20251217_112631",
  "policy_sha256": "N/A",
  "router_sha256": "N/A",
  "manifest_sha256": "N/A",
  "entry_snapshot": {
    "trade_id": "SIM-1765974369-004145",
    "entry_time": "2025-02-20T16:35:00+00:00",
    "instrument": "XAU_USD",
    "side": "long",
    "entry_price": 2944.76,
    "session": "US",
    "regime": null,
    "entry_model_version": "ENTRY_V9",
    "entry_score": {
      "p_long": 0.8525510430335999,
      "p_short": 0.14744895696640015,
      "p_hat": 0.8525510430335999,
      "margin": 0.7051020860671997
    },
    "entry_filters_passed": [
      "spread_ok",
      "atr_ok",
      "session_ok"
    ],
    "entry_filters_blocked": [],
    "test_mode": false
  },
  "feature_context": {
    "atr": {
      "atr_bps": 8.737855363507636,
      "atr_price": 2.573088696024275,
      "atr_percentile": 82.5
    },
    "range": {
      "range_pos": 0.6684993531694704,
      "distance_to_range": 0.6630012936610592,
      "range_edge_dist_atr": 3.9835393221529665
    },
    "spread": {
      "spread_price": 0.5300000000002001,
      "spread_pct": 59.5
    },
    "candle": {
      "close": 2944.495,
      "high": 2945.64,
      "low": 2944.005
    }
  },
  "router_explainability": null,
  "exit_configuration": null,
  "exit_events": [],
  "execution_events": [],
  "exit_summary": null
}