{
  "trade_id": "SIM-1765978507-001066",
  "run_tag": "replay_20251217_132717",
  "policy_sha256": "N/A",
  "router_sha256": "N/A",
  "manifest_sha256": "N/A",
  "entry_snapshot": {
    "trade_id": "SIM-1765978507-001066",
    "entry_time": "2025-03-27T19:20:00+00:00",
    "instrument": "XAU_USD",
    "side": "long",
    "entry_price": 3057.48,
    "session": "US",
    "regime": null,
    "entry_model_version": "ENTRY_V9",
    "entry_score": {
      "p_long": 0.8773970603942871,
      "p_short": 0.12260293960571289,
      "p_hat": 0.8773970603942871,
      "margin": 0.7547941207885742
    },
    "entry_filters_passed": [
      "spread_ok",
      "atr_ok",
      "session_ok"
    ],
    "entry_filters_blocked": [],
    "test_mode": false
  },
  "feature_context": {
    "atr": {
      "atr_bps": 3.482428630072883,
      "atr_price": 1.0647455887875237,
      "atr_percentile": 3.833333333333333
    },
    "range": {
      "range_pos": 0.8845129375951185,
      "distance_to_range": 0.23097412480976298,
      "range_edge_dist_atr": 2.8504461835398707
    },
    "spread": {
      "spread_price": 0.5900000000001455,
      "spread_pct": 87.5
    },
    "candle": {
      "close": 3057.185,
      "high": 3057.34,
      "low": 3056.495
    }
  },
  "router_explainability": null,
  "exit_configuration": null,
  "exit_events": [],
  "execution_events": [],
  "exit_summary": null
}