{
  "trade_id": "SIM-1765980105-000097",
  "run_tag": "replay_20251217_140118",
  "policy_sha256": "N/A",
  "router_sha256": "N/A",
  "manifest_sha256": "N/A",
  "entry_snapshot": {
    "trade_id": "SIM-1765980105-000097",
    "entry_time": "2025-03-19T18:45:00+00:00",
    "instrument": "XAU_USD",
    "side": "long",
    "entry_price": 3044.93,
    "session": "US",
    "regime": null,
    "entry_model_version": "ENTRY_V9",
    "entry_score": {
      "p_long": 0.9691363573074341,
      "p_short": 0.030863642692565918,
      "p_hat": 0.9691363573074341,
      "margin": 0.9382727146148682
    },
    "entry_filters_passed": [
      "spread_ok",
      "atr_ok",
      "session_ok"
    ],
    "entry_filters_blocked": [],
    "test_mode": false
  },
  "feature_context": {
    "atr": {
      "atr_bps": 11.472019650232346,
      "atr_price": 3.4931496793581975,
      "atr_percentile": 100.0
    },
    "range": {
      "range_pos": 0.9658941845212178,
      "distance_to_range": 0.06821163095756444,
      "range_edge_dist_atr": 0.22329418192668346
    },
    "spread": {
      "spread_price": 0.5099999999997635,
      "spread_pct": 26.041666666666668
    },
    "candle": {
      "close": 3044.675,
      "high": 3048.71,
      "low": 3044.4
    }
  },
  "router_explainability": null,
  "exit_configuration": null,
  "exit_events": [],
  "execution_events": [],
  "exit_summary": null
}