{
  "trade_id": "SIM-1765974202-004058",
  "run_tag": "replay_20251217_112631",
  "policy_sha256": "N/A",
  "router_sha256": "N/A",
  "manifest_sha256": "N/A",
  "entry_snapshot": {
    "trade_id": "SIM-1765974202-004058",
    "entry_time": "2025-02-19T17:55:00+00:00",
    "instrument": "XAU_USD",
    "side": "long",
    "entry_price": 2924.2,
    "session": "US",
    "regime": null,
    "entry_model_version": "ENTRY_V9",
    "entry_score": {
      "p_long": 0.8740525841712952,
      "p_short": 0.12594741582870483,
      "p_hat": 0.8740525841712952,
      "margin": 0.7481051683425903
    },
    "entry_filters_passed": [
      "spread_ok",
      "atr_ok",
      "session_ok"
    ],
    "entry_filters_blocked": [],
    "test_mode": false
  },
  "feature_context": {
    "atr": {
      "atr_bps": 6.600784227887574,
      "atr_price": 1.9302013239188842,
      "atr_percentile": 54.0
    },
    "range": {
      "range_pos": 0.12529411764706525,
      "distance_to_range": 0.2505882352941305,
      "range_edge_dist_atr": 1.6552677487099434
    },
    "spread": {
      "spread_price": 0.6099999999996726,
      "spread_pct": 91.83333333333333
    },
    "candle": {
      "close": 2923.895,
      "high": 2924.865,
      "low": 2923.485
    }
  },
  "router_explainability": null,
  "exit_configuration": null,
  "exit_events": [],
  "execution_events": [],
  "exit_summary": null
}